doculog/__init__.py
doculog/changelog.py
doculog/config.py
doculog/git.py
doculog/main.py
doculog/requests.py
doculog-0.1.6.dist-info/LICENSE
doculog-0.1.6.dist-info/METADATA
doculog-0.1.6.dist-info/WHEEL
doculog-0.1.6.dist-info/entry_points.txt
doculog-0.1.6.dist-info/top_level.txt
doculog-0.1.6.dist-info/RECORD
