Metadata-Version: 2.1
Name: doculog
Version: 0.1.6
Summary: Autogenerate CHANGELOG/release notes from git history
Home-page: https://github.com/DocumaticAI/doculog
Author: Documatic
Author-email: info@documatic.com
License: UNKNOWN
Project-URL: Bug Tracker, https://github.com/DocumaticAI/doculog/issues
Platform: UNKNOWN
Classifier: Programming Language :: Python :: 3
Classifier: License :: OSI Approved :: GNU General Public License v3 (GPLv3)
Classifier: Operating System :: OS Independent
Classifier: Intended Audience :: Developers
Classifier: Topic :: Documentation
Classifier: Topic :: Software Development :: Documentation
License-File: LICENSE
Requires-Dist: requests
Requires-Dist: python-dotenv
